{
    "cloudflarecommunity": {
        "url": "https://community.cloudflare.com/u/upliftedl",
        "exists": false,
        "avatar": null,
        "activity": null
    },
    "allmylinks": {
        "url": "https://allmylinks.com/upliftedl",
        "exists": false,
        "avatar": null,
        "activity": null
    },
    "codepen": {
        "url": "https://codepen.io/upliftedl",
        "exists": false,
        "avatar": null,
        "activity": null
    },
    "empretienda ar": {
        "url": "https://upliftedl.empretienda.com.ar",
        "error": "Cannot connect to host upliftedl.empretienda.com.ar:443 ssl:default [getaddrinfo failed]"
    },
    "bookcrossing": {
        "url": "https://www.bookcrossing.com/mybookshelf/upliftedl/",
        "exists": false,
        "avatar": null,
        "activity": null
    },
    "clapper": {
        "url": "https://clapperapp.com/upliftedl",
        "exists": false,
        "avatar": null,
        "activity": null
    },
    "dealabs": {
        "url": "https://www.dealabs.com/profile/upliftedl",
        "exists": false,
        "avatar": null,
        "activity": null
    },
    "discogs": {
        "url": "https://www.discogs.com/user/upliftedl",
        "exists": false,
        "avatar": null,
        "activity": null
    },
    "discord": {
        "url": "https://discord.com",
        "exists": false,
        "avatar": null,
        "activity": null
    },
    "atcoder": {
        "url": "https://atcoder.jp/users/upliftedl",
        "exists": false,
        "avatar": null,
        "activity": null
    },
    "exposure": {
        "url": "https://upliftedl.exposure.co/",
        "exists": false,
        "avatar": null,
        "activity": null
    },
    "buymeacoffee": {
        "url": "https://buymeacoff.ee/upliftedl",
        "exists": false,
        "avatar": null,
        "activity": null
    },
    "audiojungle": {
        "url": "https://audiojungle.net/user/upliftedl",
        "exists": true,
        "avatar": null,
        "activity": null
    },
    "dailymotion": {
        "url": "https://www.dailymotion.com/upliftedl",
        "exists": false,
        "avatar": null,
        "activity": null
    },
    "anilist": {
        "url": "https://anilist.co/user/upliftedl/",
        "exists": false,
        "avatar": null,
        "activity": null
    },
    "bitbucket": {
        "url": "https://bitbucket.org/upliftedl/",
        "exists": false,
        "avatar": null,
        "activity": null
    },
    "codecademy": {
        "url": "https://www.codecademy.com/profiles/upliftedl",
        "exists": true,
        "avatar": null,
        "activity": null
    },
    "codewars": {
        "url": "https://www.codewars.com/users/upliftedl",
        "exists": true,
        "avatar": null,
        "activity": null
    },
    "bitwarden forum": {
        "url": "https://community.bitwarden.com/u/upliftedl/summary",
        "exists": false,
        "avatar": null,
        "activity": null
    },
    "asciinema": {
        "url": "https://asciinema.org/~upliftedl",
        "exists": false,
        "avatar": null,
        "activity": null
    },
    "chaos": {
        "url": "https://chaos.social/@upliftedl",
        "exists": false,
        "avatar": null,
        "activity": null
    },
    "dev community": {
        "url": "https://dev.to/upliftedl",
        "exists": false,
        "avatar": null,
        "activity": null
    },
    "codechef": {
        "url": "https://www.codechef.com/users/upliftedl",
        "exists": false,
        "avatar": null,
        "activity": null
    },
    "codeberg": {
        "url": "https://codeberg.org/upliftedl",
        "exists": false,
        "avatar": null,
        "activity": null
    },
    "gumroad": {
        "url": "https://www.gumroad.com/upliftedl",
        "exists": true,
        "avatar": null,
        "activity": null
    },
    "flipboard": {
        "url": "https://flipboard.com/@upliftedl",
        "exists": true,
        "avatar": null,
        "activity": null
    },
    "carbonmade": {
        "url": "https://upliftedl.carbonmade.com",
        "exists": false,
        "avatar": null,
        "activity": null
    },
    "chaos.social": {
        "url": "https://chaos.social/@upliftedl",
        "exists": false,
        "avatar": null,
        "activity": null
    },
    "7cups": {
        "url": "https://www.7cups.com/@upliftedl",
        "exists": false,
        "avatar": null,
        "activity": null
    },
    "gesundheitsfrage": {
        "url": "https://www.gesundheitsfrage.net/nutzer/upliftedl",
        "exists": false,
        "avatar": null,
        "activity": null
    },
    "coderwall": {
        "url": "https://coderwall.com/upliftedl",
        "exists": true,
        "avatar": null,
        "activity": null
    },
    "discuss.elastic.co": {
        "url": "https://discuss.elastic.co/u/upliftedl",
        "exists": true,
        "avatar": null,
        "activity": null
    },
    "coinvote": {
        "url": "https://coinvote.cc/profile/upliftedl",
        "exists": false,
        "avatar": null,
        "activity": null
    },
    "bugcrowd": {
        "url": "https://bugcrowd.com/upliftedl",
        "exists": false,
        "avatar": null,
        "activity": null
    },
    "career.habr": {
        "url": "https://career.habr.com/upliftedl",
        "exists": true,
        "avatar": null,
        "activity": null
    },
    "crevado": {
        "url": "https://upliftedl.crevado.com",
        "exists": true,
        "avatar": null,
        "activity": null
    },
    "ctan": {
        "url": "https://ctan.org/author/upliftedl",
        "exists": false,
        "avatar": null,
        "activity": null
    },
    "dribbble": {
        "url": "https://dribbble.com/upliftedl",
        "exists": true,
        "avatar": null,
        "activity": null
    },
    "hugging face": {
        "url": "https://huggingface.co/upliftedl",
        "exists": true,
        "avatar": null,
        "activity": null
    },
    "finanzfrage": {
        "url": "https://www.finanzfrage.net/nutzer/upliftedl",
        "exists": false,
        "avatar": null,
        "activity": null
    },
    "clubhouse": {
        "url": "https://www.clubhouse.com/@upliftedl",
        "exists": false,
        "avatar": null,
        "activity": null
    },
    "cyberdefenders": {
        "url": "https://cyberdefenders.org/p/upliftedl",
        "exists": true,
        "avatar": null,
        "activity": null
    },
    "twitter": {
        "url": "https://x.com/upliftedl",
        "error": "400, message='Got more than 8190 bytes (10054) when reading Header value is too long.', url='https://x.com/upliftedl'"
    },
    "slant": {
        "url": "https://www.slant.co/users/upliftedl",
        "exists": false,
        "avatar": null,
        "activity": null
    },
    "cnet": {
        "url": "https://www.cnet.com/profiles/upliftedl/",
        "exists": true,
        "avatar": null,
        "activity": null
    },
    "crowdin": {
        "url": "https://crowdin.com/profile/upliftedl",
        "exists": true,
        "avatar": null,
        "activity": null
    },
    "toster": {
        "url": "https://www.toster.ru/user/upliftedl/answers",
        "exists": false,
        "avatar": null,
        "activity": null
    },
    "docker hub": {
        "url": "https://hub.docker.com/u/upliftedl/",
        "exists": true,
        "avatar": null,
        "activity": null
    },
    "duolingo": {
        "url": "https://www.duolingo.com/profile/upliftedl",
        "exists": false,
        "avatar": null,
        "activity": null
    },
    "disqus": {
        "url": "https://disqus.com/upliftedl",
        "exists": false,
        "avatar": null,
        "activity": null
    },
    "about.me": {
        "url": "https://about.me/upliftedl",
        "exists": true,
        "avatar": null,
        "activity": null
    },
    "packagist": {
        "url": "https://packagist.org/packages/upliftedl/",
        "exists": false,
        "avatar": null,
        "activity": null
    },
    "soundcloud": {
        "url": "https://soundcloud.com/upliftedl",
        "exists": true,
        "avatar": null,
        "activity": null
    },
    "listed": {
        "url": "https://listed.to/@upliftedl",
        "exists": false,
        "avatar": null,
        "activity": null
    },
    "gutefrage": {
        "url": "https://www.gutefrage.net/nutzer/upliftedl",
        "exists": false,
        "avatar": null,
        "activity": null
    },
    "znanylekarz.pl": {
        "url": "https://www.znanylekarz.pl/upliftedl",
        "exists": false,
        "avatar": null,
        "activity": null
    },
    "1337x": {
        "url": "https://www.1337x.to/user/upliftedl/",
        "exists": true,
        "avatar": null,
        "activity": null
    },
    "avizo": {
        "url": "https://www.avizo.cz/upliftedl/",
        "exists": false,
        "avatar": null,
        "activity": null
    },
    "clozemaster": {
        "url": "https://www.clozemaster.com/players/upliftedl",
        "exists": true,
        "avatar": null,
        "activity": null
    },
    "academia.edu": {
        "url": "https://independent.academia.edu/upliftedl",
        "exists": false,
        "avatar": null,
        "activity": null
    },
    "eintracht frankfurt forum": {
        "url": "https://community.eintracht.de/fans/upliftedl",
        "exists": true,
        "avatar": null,
        "activity": null
    },
    "livelib": {
        "url": "https://www.livelib.ru/reader/upliftedl",
        "exists": false,
        "avatar": null,
        "activity": null
    },
    "all things worn": {
        "url": "https://www.allthingsworn.com/profile/upliftedl",
        "exists": true,
        "avatar": null,
        "activity": null
    },
    "airbit": {
        "url": "https://airbit.com/upliftedl",
        "exists": true,
        "avatar": null,
        "activity": null
    },
    "traktrain": {
        "url": "https://traktrain.com/upliftedl",
        "exists": true,
        "avatar": null,
        "activity": null
    },
    "fixya": {
        "url": "https://www.fixya.com/users/upliftedl",
        "exists": false,
        "avatar": null,
        "activity": null
    },
    "apple developer": {
        "url": "https://developer.apple.com/forums/profile/upliftedl",
        "exists": true,
        "avatar": null,
        "activity": null
    },
    "getmyuni": {
        "url": "https://www.getmyuni.com/user/upliftedl",
        "exists": false,
        "avatar": null,
        "activity": null
    },
    "ultimate-guitar": {
        "url": "https://ultimate-guitar.com/u/upliftedl",
        "exists": false,
        "avatar": null,
        "activity": null
    },
    "2dimensions": {
        "url": "https://2Dimensions.com/a/upliftedl",
        "exists": true,
        "avatar": null,
        "activity": null
    },
    "harvard scholar": {
        "url": "https://scholar.harvard.edu/upliftedl",
        "exists": false,
        "avatar": null,
        "activity": null
    },
    "moikrug": {
        "url": "https://moikrug.ru/upliftedl",
        "exists": true,
        "avatar": null,
        "activity": null
    },
    "venmo": {
        "url": "https://account.venmo.com/u/upliftedl",
        "error": "Unicode strings with encoding declaration are not supported. Please use bytes input or XML fragments without declaration."
    },
    "9gag": {
        "url": "https://www.9gag.com/u/upliftedl",
        "exists": false,
        "avatar": null,
        "activity": null
    },
    "replit.com": {
        "url": "https://replit.com/@upliftedl",
        "exists": false,
        "avatar": null,
        "activity": null
    },
    "championat": {
        "url": "https://www.championat.com/user/upliftedl",
        "exists": true,
        "avatar": null,
        "activity": null
    },
    "deviantart": {
        "url": "https://upliftedl.deviantart.com",
        "exists": true,
        "avatar": null,
        "activity": null
    },
    "contently": {
        "url": "https://upliftedl.contently.com/",
        "exists": false,
        "avatar": null,
        "activity": null
    },
    "kik": {
        "url": "https://kik.me/upliftedl",
        "exists": false,
        "avatar": null,
        "activity": null
    },
    "mixcloud": {
        "url": "https://www.mixcloud.com/upliftedl/",
        "exists": true,
        "avatar": null,
        "activity": null
    },
    "pinkbike": {
        "url": "https://www.pinkbike.com/u/upliftedl/",
        "exists": false,
        "avatar": null,
        "activity": null
    },
    "hackerone": {
        "url": "https://hackerone.com/upliftedl",
        "exists": true,
        "avatar": null,
        "activity": null
    },
    "jimdo": {
        "url": "https://upliftedl.jimdosite.com",
        "exists": false,
        "avatar": null,
        "activity": null
    },
    "github": {
        "url": "https://www.github.com/upliftedl",
        "exists": true,
        "avatar": null,
        "activity": null
    },
    "kaggle": {
        "url": "https://www.kaggle.com/upliftedl",
        "exists": true,
        "avatar": null,
        "activity": null
    },
    "holopin": {
        "url": "https://holopin.io/@upliftedl",
        "exists": true,
        "avatar": null,
        "activity": null
    },
    "grailed": {
        "url": "https://www.grailed.com/upliftedl",
        "exists": true,
        "avatar": null,
        "activity": null
    },
    "apple discussions": {
        "url": "https://discussions.apple.com/profile/upliftedl",
        "exists": true,
        "avatar": null,
        "activity": null
    },
    "hackerrank": {
        "url": "https://hackerrank.com/upliftedl",
        "exists": false,
        "avatar": null,
        "activity": null
    },
    "monkeytype": {
        "url": "https://monkeytype.com/profile/upliftedl",
        "exists": true,
        "avatar": null,
        "activity": null
    },
    "pentesterlab": {
        "url": "https://pentesterlab.com/profile/upliftedl",
        "exists": false,
        "avatar": null,
        "activity": null
    },
    "needrom": {
        "url": "https://www.needrom.com/author/upliftedl/",
        "error": "Server disconnected"
    },
    "nextcloud forum": {
        "url": "https://help.nextcloud.com/u/upliftedl/summary",
        "exists": false,
        "avatar": null,
        "activity": null
    },
    "biggerpockets": {
        "url": "https://www.biggerpockets.com/users/upliftedl",
        "exists": true,
        "avatar": null,
        "activity": null
    },
    "wix": {
        "url": "https://upliftedl.wix.com",
        "exists": false,
        "avatar": null,
        "activity": null
    },
    "mstdn.io": {
        "url": "https://mstdn.io/@upliftedl",
        "exists": false,
        "avatar": null,
        "activity": null
    },
    "flickr": {
        "url": "https://www.flickr.com/people/upliftedl",
        "exists": true,
        "avatar": null,
        "activity": null
    },
    "devrant": {
        "url": "https://devrant.com/users/upliftedl",
        "exists": false,
        "avatar": null,
        "activity": null
    },
    "genius (artists)": {
        "url": "https://genius.com/artists/upliftedl",
        "exists": true,
        "avatar": null,
        "activity": null
    },
    "flightradar24": {
        "url": "https://my.flightradar24.com/upliftedl",
        "exists": true,
        "avatar": null,
        "activity": null
    },
    "trello": {
        "url": "https://trello.com/upliftedl",
        "exists": false,
        "avatar": null,
        "activity": null
    },
    "igromania": {
        "url": "http://forum.igromania.ru/member.php?username=upliftedl",
        "exists": false,
        "avatar": null,
        "activity": null
    },
    "mastodon.xyz": {
        "url": "https://mastodon.xyz/@upliftedl",
        "exists": false,
        "avatar": null,
        "activity": null
    },
    "bandcamp": {
        "url": "https://www.bandcamp.com/upliftedl",
        "exists": true,
        "avatar": null,
        "activity": null
    },
    "soylentnews": {
        "url": "https://soylentnews.org/~upliftedl",
        "exists": true,
        "avatar": null,
        "activity": null
    },
    "rubygems": {
        "url": "https://rubygems.org/profiles/upliftedl",
        "exists": false,
        "avatar": null,
        "activity": null
    },
    "swapd": {
        "url": "https://swapd.co/u/upliftedl",
        "exists": true,
        "avatar": null,
        "activity": null
    },
    "gitlab": {
        "url": "https://gitlab.com/upliftedl",
        "exists": false,
        "avatar": null,
        "activity": null
    },
    "gitea": {
        "url": "https://gitea.com/upliftedl",
        "exists": false,
        "avatar": null,
        "activity": null
    },
    "jbzd.com.pl": {
        "url": "https://jbzd.com.pl/uzytkownik/upliftedl",
        "exists": true,
        "avatar": null,
        "activity": null
    },
    "jellyfin weblate": {
        "url": "https://translate.jellyfin.org/user/upliftedl/",
        "exists": true,
        "avatar": null,
        "activity": null
    },
    "gradle": {
        "url": "https://plugins.gradle.org/u/upliftedl",
        "exists": false,
        "avatar": null,
        "activity": null
    },
    "wicg forum": {
        "url": "https://discourse.wicg.io/u/upliftedl/summary",
        "exists": true,
        "avatar": null,
        "activity": null
    },
    "kwork": {
        "url": "https://kwork.ru/user/upliftedl",
        "exists": true,
        "avatar": null,
        "activity": null
    },
    "cgtrader": {
        "url": "https://www.cgtrader.com/upliftedl",
        "exists": true,
        "avatar": null,
        "activity": null
    },
    "eintracht": {
        "url": "https://community.eintracht.de/fans/upliftedl",
        "exists": true,
        "avatar": null,
        "activity": null
    },
    "notabug.org": {
        "url": "https://notabug.org/upliftedl",
        "exists": false,
        "avatar": null,
        "activity": null
    },
    "patreon": {
        "url": "https://www.patreon.com/upliftedl",
        "exists": true,
        "avatar": null,
        "activity": null
    },
    "hudsonrock": {
        "url": "https://cavalier.hudsonrock.com/api/json/v2/osint-tools/search-by-username?username=upliftedl",
        "exists": true,
        "avatar": null,
        "activity": null
    },
    "leetcode": {
        "url": "https://leetcode.com/upliftedl",
        "exists": false,
        "avatar": null,
        "activity": null
    },
    "lesswrong": {
        "url": "https://www.lesswrong.com/users/@upliftedl",
        "exists": false,
        "avatar": null,
        "activity": null
    },
    "tellonym.me": {
        "url": "https://tellonym.me/upliftedl",
        "exists": false,
        "avatar": null,
        "activity": null
    },
    "itemfix": {
        "url": "https://www.itemfix.com/c/upliftedl",
        "exists": true,
        "avatar": null,
        "activity": null
    },
    "splice": {
        "url": "https://splice.com/upliftedl",
        "exists": true,
        "avatar": null,
        "activity": null
    },
    "scribd": {
        "url": "https://www.scribd.com/upliftedl",
        "exists": true,
        "avatar": null,
        "activity": null
    },
    "nnru": {
        "url": "https://upliftedl.www.nn.ru/",
        "exists": true,
        "avatar": null,
        "activity": null
    },
    "bazar.cz": {
        "url": "https://www.bazar.cz/upliftedl/",
        "exists": false,
        "avatar": null,
        "activity": null
    },
    "redbubble": {
        "url": "https://www.redbubble.com/people/upliftedl",
        "exists": false,
        "avatar": null,
        "activity": null
    },
    "nightbot": {
        "url": "https://nightbot.tv/t/upliftedl/commands",
        "exists": false,
        "avatar": null,
        "activity": null
    },
    "icons8 community": {
        "url": "https://community.icons8.com/u/upliftedl/summary",
        "exists": false,
        "avatar": null,
        "activity": null
    },
    "kick": {
        "url": "https://kick.com/upliftedl",
        "exists": false,
        "avatar": null,
        "activity": null
    },
    "memrise": {
        "url": "https://www.memrise.com/user/upliftedl/",
        "exists": false,
        "avatar": null,
        "activity": null
    },
    "pypi": {
        "url": "https://pypi.org/user/upliftedl",
        "exists": false,
        "avatar": null,
        "activity": null
    },
    "hackthebox": {
        "url": "https://forum.hackthebox.com/u/upliftedl",
        "exists": false,
        "avatar": null,
        "activity": null
    },
    "gitbook": {
        "url": "https://upliftedl.gitbook.io/",
        "exists": false,
        "avatar": null,
        "activity": null
    },
    "sbazar.cz": {
        "url": "https://www.sbazar.cz/upliftedl",
        "exists": true,
        "avatar": null,
        "activity": null
    },
    "linkedin": {
        "url": "https://linkedin.com/in/upliftedl",
        "exists": true,
        "avatar": null,
        "activity": null
    },
    "smule": {
        "url": "https://www.smule.com/upliftedl",
        "exists": true,
        "avatar": null,
        "activity": null
    },
    "telegram": {
        "url": "https://t.me/upliftedl",
        "exists": false,
        "avatar": null,
        "activity": null
    },
    "archive.org": {
        "url": "https://archive.org/details/@upliftedl",
        "exists": false,
        "avatar": null,
        "activity": null
    },
    "freelance.habr": {
        "url": "https://freelance.habr.com/freelancers/upliftedl",
        "exists": false,
        "avatar": null,
        "activity": null
    },
    "youtube": {
        "url": "https://www.youtube.com/@upliftedl",
        "exists": false,
        "avatar": null,
        "activity": null
    },
    "football": {
        "url": "https://www.rusfootball.info/user/upliftedl/",
        "exists": true,
        "avatar": null,
        "activity": null
    },
    "vk": {
        "url": "https://vk.com/upliftedl",
        "error": "Cannot connect to host vk.com:443 ssl:default [The specified network name is no longer available]"
    },
    "trashboxru": {
        "url": "https://trashbox.ru/users/upliftedl",
        "exists": false,
        "avatar": null,
        "activity": null
    },
    "wikidot": {
        "url": "http://www.wikidot.com/user:info/upliftedl",
        "exists": true,
        "avatar": null,
        "activity": null
    },
    "mercadolivre": {
        "url": "https://www.mercadolivre.com.br/perfil/upliftedl",
        "exists": true,
        "avatar": null,
        "activity": null
    },
    "opennet": {
        "url": "https://www.opennet.ru/~upliftedl",
        "exists": true,
        "avatar": null,
        "activity": null
    },
    "nintendolife": {
        "url": "https://www.nintendolife.com/users/upliftedl",
        "exists": true,
        "avatar": null,
        "activity": null
    },
    "gitee": {
        "url": "https://gitee.com/upliftedl",
        "exists": false,
        "avatar": null,
        "activity": null
    },
    "younow": {
        "url": "https://www.younow.com/upliftedl/",
        "exists": false,
        "avatar": null,
        "activity": null
    },
    "social.tchncs.de": {
        "url": "https://social.tchncs.de/@upliftedl",
        "exists": false,
        "avatar": null,
        "activity": null
    },
    "sublimeforum": {
        "url": "https://forum.sublimetext.com/u/upliftedl",
        "exists": false,
        "avatar": null,
        "activity": null
    },
    "scratch": {
        "url": "https://scratch.mit.edu/users/upliftedl",
        "exists": false,
        "avatar": null,
        "activity": null
    },
    "geeksforgeeks": {
        "url": "https://auth.geeksforgeeks.org/user/upliftedl",
        "exists": false,
        "avatar": null,
        "activity": null
    },
    "webnode": {
        "url": "https://upliftedl.webnode.cz/",
        "exists": false,
        "avatar": null,
        "activity": null
    },
    "f3.cool": {
        "url": "https://f3.cool/upliftedl/",
        "exists": false,
        "avatar": null,
        "activity": null
    },
    "wikipedia": {
        "url": "https://en.wikipedia.org/wiki/Special:CentralAuth/upliftedl?uselang=qqx",
        "exists": true,
        "avatar": null,
        "activity": null
    },
    "npm": {
        "url": "https://www.npmjs.com/~upliftedl",
        "exists": true,
        "avatar": null,
        "activity": null
    },
    "hashnode": {
        "url": "https://hashnode.com/@upliftedl",
        "exists": true,
        "avatar": null,
        "activity": null
    },
    "vimeo": {
        "url": "https://vimeo.com/upliftedl",
        "exists": true,
        "avatar": null,
        "activity": null
    },
    "tweakers": {
        "url": "https://tweakers.net/gallery/upliftedl",
        "exists": true,
        "avatar": null,
        "activity": null
    },
    "yandexmusic": {
        "url": "https://music.yandex/users/upliftedl/playlists",
        "exists": false,
        "avatar": null,
        "activity": null
    },
    "sessionize": {
        "url": "https://sessionize.com/upliftedl",
        "exists": false,
        "avatar": null,
        "activity": null
    },
    "topcoder": {
        "url": "https://profiles.topcoder.com/upliftedl/",
        "exists": false,
        "avatar": null,
        "activity": null
    },
    "d3ru": {
        "url": "https://d3.ru/user/upliftedl/posts",
        "exists": true,
        "avatar": null,
        "activity": null
    },
    "xvideos": {
        "url": "https://xvideos.com/profiles/upliftedl",
        "error": "Cannot connect to host xvideos.com:443 ssl:default [The specified network name is no longer available]"
    },
    "hackerearth": {
        "url": "https://hackerearth.com/@upliftedl",
        "exists": true,
        "avatar": null,
        "activity": null
    },
    "rumble": {
        "url": "https://rumble.com/user/upliftedl",
        "error": "[WinError 10054] An existing connection was forcibly closed by the remote host"
    },
    "wordnik": {
        "url": "https://www.wordnik.com/users/upliftedl",
        "exists": true,
        "avatar": null,
        "activity": null
    },
    "tiendanube": {
        "url": "https://upliftedl.mitiendanube.com/",
        "exists": false,
        "avatar": null,
        "activity": null
    },
    "pr0gramm": {
        "url": "https://pr0gramm.com/user/upliftedl",
        "exists": false,
        "avatar": null,
        "activity": null
    },
    "themeforest": {
        "url": "https://themeforest.net/user/upliftedl",
        "exists": true,
        "avatar": null,
        "activity": null
    },
    "genius (users)": {
        "url": "https://genius.com/upliftedl",
        "exists": true,
        "avatar": null,
        "activity": null
    },
    "gnome vcs": {
        "url": "https://gitlab.gnome.org/upliftedl",
        "exists": false,
        "avatar": null,
        "activity": null
    },
    "polygon": {
        "url": "https://www.polygon.com/users/upliftedl",
        "exists": true,
        "avatar": null,
        "activity": null
    },
    "splits.io": {
        "url": "https://splits.io/users/upliftedl",
        "exists": false,
        "avatar": null,
        "activity": null
    },
    "launchpad": {
        "url": "https://launchpad.net/~upliftedl",
        "exists": true,
        "avatar": null,
        "activity": null
    },
    "opensource": {
        "url": "https://opensource.com/users/upliftedl",
        "exists": false,
        "avatar": null,
        "activity": null
    },
    "weebly": {
        "url": "https://upliftedl.weebly.com/",
        "exists": false,
        "avatar": null,
        "activity": null
    },
    "uid": {
        "url": "http://uid.me/upliftedl",
        "exists": false,
        "avatar": null,
        "activity": null
    },
    "intigriti": {
        "url": "https://app.intigriti.com/profile/upliftedl",
        "exists": true,
        "avatar": null,
        "activity": null
    },
    "warrior forum": {
        "url": "https://www.warriorforum.com/members/upliftedl.html",
        "exists": true,
        "avatar": null,
        "activity": null
    },
    "myminifactory": {
        "url": "https://www.myminifactory.com/users/upliftedl",
        "exists": false,
        "avatar": null,
        "activity": null
    },
    "egpu": {
        "url": "https://egpu.io/forums/profile/upliftedl/",
        "error": ""
    },
    "interpals": {
        "url": "https://www.interpals.net/upliftedl",
        "error": ""
    },
    "linktree": {
        "url": "https://linktr.ee/upliftedl",
        "error": ""
    },
    "habr": {
        "url": "https://habr.com/ru/users/upliftedl",
        "error": ""
    },
    "naver": {
        "url": "https://blog.naver.com/upliftedl",
        "error": ""
    },
    "hunting": {
        "url": "https://www.hunting.ru/forum/members/?username=upliftedl",
        "error": ""
    },
    "furaffinity": {
        "url": "https://www.furaffinity.net/user/upliftedl",
        "error": ""
    },
    "hackster": {
        "url": "https://www.hackster.io/upliftedl",
        "error": ""
    },
    "forum_guns": {
        "url": "https://forum.guns.ru/forummisc/blog/upliftedl",
        "error": ""
    },
    "freecodecamp": {
        "url": "https://www.freecodecamp.org/upliftedl",
        "error": ""
    },
    "librarything": {
        "url": "https://www.librarything.com/profile/upliftedl",
        "error": ""
    },
    "irecommend": {
        "url": "https://irecommend.ru/users/upliftedl",
        "error": ""
    },
    "livejournal": {
        "url": "https://upliftedl.livejournal.com",
        "error": ""
    },
    "medium": {
        "url": "https://medium.com/@upliftedl",
        "error": ""
    },
    "fandom": {
        "url": "https://www.fandom.com/u/upliftedl",
        "error": ""
    },
    "drive2": {
        "url": "https://www.drive2.ru/users/upliftedl",
        "error": ""
    },
    "babyblogru": {
        "url": "https://www.babyblog.ru/user/upliftedl",
        "error": ""
    },
    "couchsurfing": {
        "url": "https://www.couchsurfing.com/people/upliftedl",
        "error": ""
    },
    "erome": {
        "url": "https://www.erome.com/upliftedl",
        "error": ""
    },
    "lottiefiles": {
        "url": "https://lottiefiles.com/upliftedl",
        "error": ""
    },
    "letterboxd": {
        "url": "https://letterboxd.com/upliftedl",
        "error": ""
    },
    "caddy community": {
        "url": "https://caddy.community/u/upliftedl/summary",
        "error": ""
    },
    "jeuxvideo": {
        "url": "https://www.jeuxvideo.com/profil/upliftedl",
        "error": ""
    },
    "fl": {
        "url": "https://www.fl.ru/users/upliftedl",
        "error": ""
    },
    "datingru": {
        "url": "http://dating.ru/upliftedl",
        "error": ""
    },
    "dailykos": {
        "url": "https://www.dailykos.com/user/upliftedl",
        "error": ""
    },
    "lobsters": {
        "url": "https://lobste.rs/u/upliftedl",
        "error": ""
    },
    "osu!": {
        "url": "https://osu.ppy.sh/users/upliftedl",
        "error": ""
    },
    "car talk community": {
        "url": "https://community.cartalk.com/u/upliftedl/summary",
        "error": ""
    },
    "last.fm": {
        "url": "https://last.fm/user/upliftedl",
        "error": ""
    },
    "lor": {
        "url": "https://www.linux.org.ru/people/upliftedl/profile",
        "error": ""
    },
    "joplin forum": {
        "url": "https://discourse.joplinapp.org/u/upliftedl",
        "error": ""
    },
    "kofi": {
        "url": "https://ko-fi.com/upliftedl",
        "error": ""
    },
    "cssbattle": {
        "url": "https://cssbattle.dev/player/upliftedl",
        "error": ""
    },
    "lichess": {
        "url": "https://lichess.org/@/upliftedl",
        "error": ""
    },
    "envato forum": {
        "url": "https://forums.envato.com/u/upliftedl",
        "error": ""
    },
    "vero": {
        "url": "https://vero.co/upliftedl",
        "error": ""
    },
    "geocaching": {
        "url": "https://www.geocaching.com/p/default.aspx?u=upliftedl",
        "error": ""
    },
    "authorstream": {
        "url": "http://www.authorstream.com/upliftedl/",
        "error": ""
    },
    "dmoj": {
        "url": "https://dmoj.ca/user/upliftedl",
        "error": ""
    },
    "aniworld": {
        "url": "https://aniworld.to/user/profil/upliftedl",
        "error": ""
    },
    "leasehackr": {
        "url": "https://forum.leasehackr.com/u/upliftedl/summary/",
        "error": ""
    },
    "lushstories": {
        "url": "https://www.lushstories.com/profile/upliftedl",
        "error": ""
    },
    "akniga": {
        "url": "https://akniga.org/profile/upliftedl",
        "error": ""
    },
    "kongregate": {
        "url": "https://www.kongregate.com/accounts/upliftedl",
        "error": ""
    },
    "wykop": {
        "url": "https://www.wykop.pl/ludzie/upliftedl",
        "error": ""
    },
    "youpic": {
        "url": "https://youpic.com/photographer/upliftedl/",
        "error": ""
    },
    "keybase": {
        "url": "https://keybase.io/upliftedl",
        "error": ""
    },
    "kaskus": {
        "url": "https://www.kaskus.co.id/@upliftedl",
        "error": ""
    },
    "wordpressorg": {
        "url": "https://profiles.wordpress.org/upliftedl/",
        "error": ""
    },
    "xbox gamertag": {
        "url": "https://xboxgamertag.com/search/upliftedl",
        "error": ""
    },
    "wolframalphaforum": {
        "url": "https://community.wolfram.com/web/upliftedl/home",
        "error": ""
    },
    "cryptomator forum": {
        "url": "https://community.cryptomator.org/u/upliftedl",
        "error": ""
    },
    "windy": {
        "url": "https://community.windy.com/user/upliftedl",
        "error": ""
    },
    "youporn": {
        "url": "https://youporn.com/uservids/upliftedl",
        "error": ""
    },
    "mmorpg forum": {
        "url": "https://forums.mmorpg.com/profile/upliftedl",
        "error": ""
    },
    "vlr": {
        "url": "https://www.vlr.gg/user/upliftedl",
        "error": ""
    },
    "issuu": {
        "url": "https://issuu.com/upliftedl",
        "error": ""
    },
    "buzzfeed": {
        "url": "https://buzzfeed.com/upliftedl",
        "error": ""
    },
    "mastodon.cloud": {
        "url": "https://mastodon.cloud/@upliftedl",
        "error": ""
    },
    "wordpress": {
        "url": "https://upliftedl.wordpress.com/",
        "error": ""
    },
    "typeracer": {
        "url": "https://data.typeracer.com/pit/profile?user=upliftedl",
        "error": ""
    },
    "tenor": {
        "url": "https://tenor.com/users/upliftedl",
        "error": ""
    },
    "itch.io": {
        "url": "https://upliftedl.itch.io/",
        "error": ""
    },
    "virustotal": {
        "url": "https://www.virustotal.com/gui/user/upliftedl",
        "error": ""
    },
    "cracked": {
        "url": "https://www.cracked.com/members/upliftedl/",
        "error": ""
    },
    "velomania": {
        "url": "https://forum.velomania.ru/member.php?username=upliftedl",
        "error": ""
    },
    "velog": {
        "url": "https://velog.io/@upliftedl/posts",
        "error": ""
    },
    "ask fedora": {
        "url": "https://ask.fedoraproject.org/u/upliftedl",
        "error": ""
    },
    "mastodon.social": {
        "url": "https://mastodon.social/@upliftedl",
        "error": ""
    },
    "untappd": {
        "url": "https://untappd.com/user/upliftedl",
        "error": ""
    },
    "bravecommunity": {
        "url": "https://community.brave.com/u/upliftedl/",
        "error": ""
    },
    "runescape": {
        "url": "https://apps.runescape.com/runemetrics/app/overview/player/upliftedl",
        "error": ""
    },
    "airliners": {
        "url": "https://www.airliners.net/user/upliftedl/profile/photos",
        "error": ""
    },
    "weblate": {
        "url": "https://hosted.weblate.org/user/upliftedl/",
        "error": ""
    },
    "tetr.io": {
        "url": "https://ch.tetr.io/u/upliftedl",
        "error": ""
    },
    "instructables": {
        "url": "https://www.instructables.com/member/upliftedl",
        "error": ""
    },
    "hubpages": {
        "url": "https://hubpages.com/@upliftedl",
        "error": ""
    },
    "ionic forum": {
        "url": "https://forum.ionicframework.com/u/upliftedl",
        "error": ""
    },
    "instagram": {
        "url": "https://instagram.com/upliftedl",
        "error": ""
    },
    "digitalspy": {
        "url": "https://forums.digitalspy.com/profile/upliftedl",
        "error": ""
    },
    "openstreetmap": {
        "url": "https://www.openstreetmap.org/user/upliftedl",
        "error": ""
    },
    "boardgamegeek": {
        "url": "https://boardgamegeek.com/user/upliftedl",
        "error": ""
    },
    "autofrage": {
        "url": "https://www.autofrage.net/nutzer/upliftedl",
        "error": ""
    },
    "image fap": {
        "url": "https://www.imagefap.com/profile/upliftedl",
        "error": ""
    },
    "wattpad": {
        "url": "https://www.wattpad.com/user/upliftedl",
        "error": ""
    },
    "blogger": {
        "url": "https://upliftedl.blogspot.com",
        "error": ""
    },
    "vsco": {
        "url": "https://vsco.co/upliftedl",
        "error": ""
    },
    "hubski": {
        "url": "https://hubski.com/user/upliftedl",
        "error": ""
    },
    "strava": {
        "url": "https://www.strava.com/athletes/upliftedl",
        "error": ""
    },
    "gravatar": {
        "url": "http://en.gravatar.com/upliftedl",
        "error": ""
    },
    "torrentgalaxy": {
        "url": "https://torrentgalaxy.to/profile/upliftedl",
        "error": ""
    },
    "steam community (user)": {
        "url": "https://steamcommunity.com/id/upliftedl/",
        "error": ""
    },
    "ifttt": {
        "url": "https://www.ifttt.com/p/upliftedl",
        "error": ""
    },
    "coroflot": {
        "url": "https://www.coroflot.com/upliftedl",
        "error": ""
    },
    "bongacams": {
        "url": "https://pt.bongacams.com/profile/upliftedl",
        "error": ""
    },
    "imgup.cz": {
        "url": "https://imgup.cz/upliftedl",
        "error": ""
    },
    "tnaflix": {
        "url": "https://www.tnaflix.com/profile/upliftedl",
        "error": ""
    },
    "speedrun.com": {
        "url": "https://speedrun.com/users/upliftedl",
        "error": ""
    },
    "tuna": {
        "url": "https://tuna.voicemod.net/user/upliftedl",
        "error": ""
    },
    "imgur": {
        "url": "https://imgur.com/user/upliftedl",
        "error": ""
    },
    "sourceforge": {
        "url": "https://sourceforge.net/u/upliftedl",
        "error": ""
    },
    "slashdot": {
        "url": "https://slashdot.org/~upliftedl",
        "error": ""
    },
    "spotify": {
        "url": "https://open.spotify.com/user/upliftedl",
        "error": ""
    },
    "trawelling": {
        "url": "https://traewelling.de/@upliftedl",
        "error": ""
    },
    "irc-galleria": {
        "url": "https://irc-galleria.net/user/upliftedl",
        "error": ""
    },
    "houzz": {
        "url": "https://houzz.com/user/upliftedl",
        "error": ""
    },
    "slideshare": {
        "url": "https://slideshare.net/upliftedl",
        "error": ""
    },
    "hackenproof (hackers)": {
        "url": "https://hackenproof.com/hackers/upliftedl",
        "error": ""
    },
    "signal": {
        "url": "https://community.signalusers.org/u/upliftedl",
        "error": ""
    },
    "star citizen": {
        "url": "https://robertsspaceindustries.com/citizens/upliftedl",
        "error": ""
    },
    "colourlovers": {
        "url": "https://www.colourlovers.com/lover/upliftedl",
        "error": ""
    },
    "sportsru": {
        "url": "https://www.sports.ru/profile/upliftedl/",
        "error": ""
    },
    "tradingview": {
        "url": "https://www.tradingview.com/u/upliftedl/",
        "error": ""
    },
    "behance": {
        "url": "https://www.behance.net/upliftedl",
        "error": ""
    },
    "royalcams": {
        "url": "https://royalcams.com/profile/upliftedl",
        "error": ""
    },
    "spells8": {
        "url": "https://forum.spells8.com/u/upliftedl",
        "error": ""
    },
    "biohacking": {
        "url": "https://forum.dangerousthings.com/u/upliftedl",
        "error": ""
    },
    "smugmug": {
        "url": "https://upliftedl.smugmug.com",
        "error": ""
    },
    "giant bomb": {
        "url": "https://www.giantbomb.com/profile/upliftedl/",
        "error": ""
    },
    "sportlerfrage": {
        "url": "https://www.sportlerfrage.net/nutzer/upliftedl",
        "error": ""
    },
    "reisefrage": {
        "url": "https://www.reisefrage.net/nutzer/upliftedl",
        "error": ""
    },
    "cults3d": {
        "url": "https://cults3d.com/en/users/upliftedl/creations",
        "error": ""
    },
    "blipfoto": {
        "url": "https://www.blipfoto.com/upliftedl",
        "error": ""
    },
    "unsplash": {
        "url": "https://unsplash.com/@upliftedl",
        "error": ""
    },
    "playstore": {
        "url": "https://play.google.com/store/apps/developer?id=upliftedl",
        "error": ""
    },
    "tryhackme": {
        "url": "https://tryhackme.com/p/upliftedl",
        "error": ""
    },
    "slides": {
        "url": "https://slides.com/upliftedl",
        "error": ""
    },
    "researchgate": {
        "url": "https://www.researchgate.net/profile/upliftedl",
        "error": ""
    },
    "periscope": {
        "url": "https://www.periscope.tv/upliftedl/",
        "error": ""
    },
    "promodj": {
        "url": "http://promodj.com/upliftedl",
        "error": ""
    },
    "pepperit": {
        "url": "https://www.pepper.it/profile/upliftedl/overview",
        "error": ""
    },
    "trakt": {
        "url": "https://www.trakt.tv/users/upliftedl",
        "error": ""
    },
    "google play": {
        "url": "https://play.google.com/store/apps/developer?id=upliftedl",
        "error": ""
    },
    "hackernews": {
        "url": "https://news.ycombinator.com/user?id=upliftedl",
        "error": ""
    },
    "pornhub": {
        "url": "https://pornhub.com/users/upliftedl",
        "error": ""
    },
    "heavy-r": {
        "url": "https://www.heavy-r.com/user/upliftedl",
        "error": ""
    },
    "psnprofiles.com": {
        "url": "https://psnprofiles.com/upliftedl",
        "error": ""
    },
    "apclips": {
        "url": "https://apclips.com/upliftedl",
        "error": ""
    },
    "admireme.vip": {
        "url": "https://admireme.vip/upliftedl",
        "error": ""
    },
    "gamespot": {
        "url": "https://www.gamespot.com/profile/upliftedl/",
        "error": ""
    },
    "newgrounds": {
        "url": "https://upliftedl.newgrounds.com",
        "error": ""
    },
    "fanpop": {
        "url": "https://www.fanpop.com/fans/upliftedl",
        "error": ""
    },
    "chaturbate": {
        "url": "https://chaturbate.com/upliftedl",
        "error": ""
    },
    "steam community (group)": {
        "url": "https://steamcommunity.com/groups/upliftedl",
        "error": ""
    },
    "archive of our own": {
        "url": "https://archiveofourown.org/users/upliftedl",
        "error": ""
    },
    "rate your music": {
        "url": "https://rateyourmusic.com/~upliftedl",
        "error": ""
    },
    "polarsteps": {
        "url": "https://polarsteps.com/upliftedl",
        "error": ""
    },
    "nationstates region": {
        "url": "https://nationstates.net/region=upliftedl",
        "error": ""
    },
    "hackaday": {
        "url": "https://hackaday.io/upliftedl",
        "error": ""
    },
    "ourdjtalk": {
        "url": "https://ourdjtalk.com/members?username=upliftedl",
        "error": ""
    },
    "eyeem": {
        "url": "https://www.eyeem.com/u/upliftedl",
        "error": ""
    },
    "xhamster": {
        "url": "https://xhamster.com/users/upliftedl",
        "error": ""
    },
    "booth": {
        "url": "https://upliftedl.booth.pm/",
        "error": ""
    },
    "threads": {
        "url": "https://www.threads.net/@upliftedl",
        "error": ""
    },
    "spletnik": {
        "url": "https://spletnik.ru/user/upliftedl",
        "error": ""
    },
    "roblox": {
        "url": "https://www.roblox.com/user.aspx?username=upliftedl",
        "error": ""
    },
    "prog.hu": {
        "url": "https://prog.hu/azonosito/info/upliftedl",
        "error": ""
    },
    "myanimelist": {
        "url": "https://myanimelist.net/profile/upliftedl",
        "error": ""
    },
    "pikabu": {
        "url": "https://pikabu.ru/@upliftedl",
        "error": ""
    },
    "nationstates nation": {
        "url": "https://nationstates.net/nation=upliftedl",
        "error": ""
    },
    "omg.lol": {
        "url": "https://upliftedl.omg.lol",
        "error": ""
    },
    "motherless": {
        "url": "https://motherless.com/m/upliftedl",
        "error": ""
    },
    "note": {
        "url": "https://note.com/upliftedl",
        "error": ""
    },
    "nyaa.si": {
        "url": "https://nyaa.si/user/upliftedl",
        "error": ""
    },
    "nairaland.com": {
        "url": "https://www.nairaland.com/upliftedl",
        "error": ""
    },
    "minds": {
        "url": "https://www.minds.com/upliftedl/",
        "error": ""
    },
    "sporcle": {
        "url": "https://www.sporcle.com/user/upliftedl/people",
        "error": ""
    },
    "coders rank": {
        "url": "https://profile.codersrank.io/user/upliftedl/",
        "error": ""
    },
    "codeforces": {
        "url": "https://codeforces.com/profile/upliftedl",
        "error": ""
    },
    "snapchat": {
        "url": "https://www.snapchat.com/add/upliftedl",
        "error": ""
    },
    "rockettube": {
        "url": "https://www.rockettube.com/upliftedl",
        "error": ""
    },
    "goodreads": {
        "url": "https://www.goodreads.com/upliftedl",
        "error": ""
    },
    "sketchfab": {
        "url": "https://sketchfab.com/upliftedl",
        "error": ""
    },
    "bezuzyteczna": {
        "url": "https://bezuzyteczna.pl/uzytkownicy/upliftedl",
        "error": ""
    },
    "freesound": {
        "url": "https://freesound.org/people/upliftedl/",
        "error": ""
    },
    "artstation": {
        "url": "https://www.artstation.com/upliftedl",
        "error": ""
    },
    "forum ophilia": {
        "url": "https://www.forumophilia.com/profile.php?mode=viewprofile&u=upliftedl",
        "error": ""
    },
    "reddit": {
        "url": "https://www.reddit.com/user/upliftedl",
        "error": ""
    },
    "giphy": {
        "url": "https://giphy.com/upliftedl",
        "error": ""
    },
    "polymart": {
        "url": "https://polymart.org/user/upliftedl",
        "error": ""
    },
    "redtube": {
        "url": "https://www.redtube.com/users/upliftedl",
        "error": ""
    },
    "code snippet wiki": {
        "url": "https://codesnippets.fandom.com/wiki/User:upliftedl",
        "error": ""
    },
    "rclone forum": {
        "url": "https://forum.rclone.org/u/upliftedl",
        "error": ""
    },
    "freelancer": {
        "url": "https://www.freelancer.com/u/upliftedl",
        "error": ""
    },
    "pocketstars": {
        "url": "https://pocketstars.com/upliftedl",
        "error": ""
    },
    "rajce.net": {
        "url": "https://upliftedl.rajce.idnes.cz/",
        "error": ""
    },
    "reverbnation": {
        "url": "https://www.reverbnation.com/upliftedl",
        "error": ""
    },
    "fosstodon": {
        "url": "https://fosstodon.org/@upliftedl",
        "error": ""
    },
    "fortnitetracker": {
        "url": "https://fortnitetracker.com/profile/all/upliftedl",
        "error": ""
    },
    "producthunt": {
        "url": "https://www.producthunt.com/@upliftedl",
        "error": ""
    },
    "pcgamer": {
        "url": "https://forums.pcgamer.com/members/?username=upliftedl",
        "error": ""
    },
    "rarible": {
        "url": "https://rarible.com/marketplace/api/v4/urls/upliftedl",
        "error": ""
    },
    "nitrotype": {
        "url": "https://www.nitrotype.com/racer/upliftedl",
        "error": ""
    },
    "choice community": {
        "url": "https://choice.community/u/upliftedl/summary",
        "error": ""
    },
    "chess": {
        "url": "https://www.chess.com/member/upliftedl",
        "error": ""
    },
    "gaiaonline": {
        "url": "https://www.gaiaonline.com/profiles/upliftedl",
        "error": ""
    },
    "fameswap": {
        "url": "https://fameswap.com/user/upliftedl",
        "error": ""
    },
    "nicommunityforum": {
        "url": "https://community.native-instruments.com/profile/upliftedl",
        "error": ""
    },
    "myspace": {
        "url": "https://myspace.com/upliftedl",
        "error": ""
    },
    "chatujme.cz": {
        "url": "https://profil.chatujme.cz/upliftedl",
        "error": ""
    },
    "pokemon showdown": {
        "url": "https://pokemonshowdown.com/users/upliftedl",
        "error": ""
    },
    "mydramalist": {
        "url": "https://www.mydramalist.com/profile/upliftedl",
        "error": ""
    },
    "bluesky": {
        "url": "https://bsky.app/profile/upliftedl.bsky.social",
        "error": ""
    },
    "ninja kiwi": {
        "url": "https://ninjakiwi.com/profile/upliftedl",
        "error": ""
    },
    "svidbook": {
        "url": "https://www.svidbook.ru/user/upliftedl",
        "error": ""
    },
    "shitpostbot5000": {
        "url": "https://www.shitpostbot.com/user/upliftedl",
        "error": ""
    },
    "pastebin": {
        "url": "https://pastebin.com/u/upliftedl",
        "error": ""
    },
    "slack": {
        "url": "https://upliftedl.slack.com",
        "error": ""
    },
    "satsisru": {
        "url": "https://satsis.info/user/upliftedl",
        "error": ""
    },
    "exophase": {
        "url": "https://www.exophase.com/user/upliftedl/",
        "error": ""
    },
    "phpru": {
        "url": "https://php.ru/forum/members/?username=upliftedl",
        "error": ""
    },
    "motorradfrage": {
        "url": "https://www.motorradfrage.net/nutzer/upliftedl",
        "error": ""
    },
    "minecraft": {
        "url": "https://api.mojang.com/users/profiles/minecraft/upliftedl",
        "error": ""
    }
}